ddt/__init__.py
ddt/__main__.py
ddt/cli.py
ddt/config.py
ddt/models.py
ddt/tokenizer.py
ddt_llm-0.1.2.dist-info/METADATA
ddt_llm-0.1.2.dist-info/WHEEL
ddt_llm-0.1.2.dist-info/entry_points.txt
ddt_llm-0.1.2.dist-info/licenses/LICENSE
ddt_llm-0.1.2.dist-info/RECORD
