Metadata-Version: 2.4
Name: ddt-llm
Version: 0.1.2
Summary: A CLI tool that crawls a directory and counts the tokens per filetype
License-Expression: MIT
License-File: LICENSE
Requires-Python: >=3.13
Requires-Dist: jinja2>=3.1.6
Requires-Dist: openai>=1.63.2
Requires-Dist: pillow>=11.1.0
Requires-Dist: tiktoken>=0.9.0
